stdio/__init__.py
stdio/loader.py
stdio/read.py
stdio/write.py
stdio-1.0.1.dist-info/LICENSE
stdio-1.0.1.dist-info/METADATA
stdio-1.0.1.dist-info/WHEEL
stdio-1.0.1.dist-info/top_level.txt
stdio-1.0.1.dist-info/zip-safe
stdio-1.0.1.dist-info/RECORD
