Metadata-Version: 2.1
Name: stdio
Version: 1.0.1
Summary: Facilitating functions related to reading and writing data on the terminal.
Home-page: https://github.com/duxtec/pystdio
Author: Dux Tecnologia
Author-email: contato@dux.tec.br
License: GPLv3
Classifier: Development Status :: 3 - Alpha
Classifier: Intended Audience :: Education
Classifier: License :: OSI Approved :: GNU General Public License v3 (GPLv3)
Classifier: Programming Language :: Python :: 3
Classifier: Programming Language :: Python :: 3.6
Classifier: Programming Language :: Python :: 3.7
Classifier: Programming Language :: Python :: 3.8
Classifier: Programming Language :: Python :: 3.9
Classifier: Programming Language :: Python :: 3.10
Classifier: Programming Language :: Python :: 3.11
Requires-Python: >=3.6
License-File: LICENSE
